[
  {
    "id": 1,
    "dealerId": 1,
    "name": "Ur Consulting GmbH Autohaus",
    "logo": "https://source.unsplash.com/200x200?brandenburg",
    "openingHours": {
      "sunday": {
        "from": "closed"
      },
      "Monday": {
        "from": "10 AM",
        "to": "17 PM"
      },
      "Tuesday": {
        "from": "10 AM",
        "to": "17 PM"
      },
      "Wednesday": {
        "from": "10 AM",
        "to": "17 PM"
      },
      "Thrusday": {
        "from": "10 AM",
        "to": "17 PM"
      },
      "Friday": {
        "from": "10 AM",
        "to": "17 PM"
      },
      "Saturday": {
        "from": "10 AM",
        "to": "13 PM"
      }
    },
    "address": {
      "streetAddress": "Finowfurter Ring 47",
      "addressLocality": "Brandenburg",
      "postalCode": "16244",
      "addressCountry": "DE"
    },
    "geo": { "lat": 52.84707, "lng": 13.6922 }
  },
  {
    "id": 2,
    "dealerId": 2,
    "name": "Autohandel Nicolaus",
    "logo": "https://source.unsplash.com/200x200?potsdam",
    "openingHours": {
      "sunday": {
        "from": "closed"
      },
      "Monday": {
        "from": "10 AM",
        "to": "17 PM"
      },
      "Tuesday": {
        "from": "10 AM",
        "to": "17 PM"
      },
      "Wednesday": {
        "from": "10 AM",
        "to": "17 PM"
      },
      "Thrusday": {
        "from": "10 AM",
        "to": "17 PM"
      },
      "Friday": {
        "from": "10 AM",
        "to": "17 PM"
      },
      "Saturday": {
        "from": "10 AM",
        "to": "13 PM"
      }
    },
    "address": {
      "streetAddress": "Am Buchhorst 26",
      "addressLocality": "Potsdam",
      "postalCode": "14478",
      "addressCountry": "DE"
    },
    "geo": { "lat": 52.35786, "lng": 13.10857 }
  },
  {
    "id": 3,
    "dealerId": 3,
    "name": "Autohaus Golbeck GmbH",
    "logo": "https://source.unsplash.com/200x200?friedrichshain",
    "openingHours": {
      "sunday": {
        "from": "closed"
      },
      "Monday": {
        "from": "10 AM",
        "to": "17 PM"
      },
      "Tuesday": {
        "from": "10 AM",
        "to": "17 PM"
      },
      "Wednesday": {
        "from": "10 AM",
        "to": "17 PM"
      },
      "Thrusday": {
        "from": "10 AM",
        "to": "17 PM"
      },
      "Friday": {
        "from": "10 AM",
        "to": "17 PM"
      },
      "Saturday": {
        "from": "10 AM",
        "to": "13 PM"
      }
    },
    "address": {
      "streetAddress": "Kreutzigerstraße 28",
      "addressLocality": "Berlin",
      "postalCode": "10247",
      "addressCountry": "DE"
    },
    "geo": { "lat": 52.5144, "lng": 13.46115 }
  },
  {
    "id": 4,
    "dealerId": 4,
    "name": "Volkswagen Automobile Berlin GmbH Service",
    "logo": "https://source.unsplash.com/200x200?charlottenburg",
    "openingHours": {
      "sunday": {
        "from": "closed"
      },
      "Monday": {
        "from": "10 AM",
        "to": "17 PM"
      },
      "Tuesday": {
        "from": "10 AM",
        "to": "17 PM"
      },
      "Wednesday": {
        "from": "10 AM",
        "to": "17 PM"
      },
      "Thrusday": {
        "from": "10 AM",
        "to": "17 PM"
      },
      "Friday": {
        "from": "10 AM",
        "to": "17 PM"
      },
      "Saturday": {
        "from": "10 AM",
        "to": "13 PM"
      }
    },
    "address": {
      "streetAddress": "Franklinstraße 5",
      "addressLocality": "Berlin",
      "postalCode": "10587",
      "addressCountry": "DE"
    },
    "geo": { "lat": 52.51886, "lng": 13.32656 }
  },
  {
    "id": 5,
    "dealerId": 5,
    "name": "Autohaus Wedding GmbH",
    "logo": "https://source.unsplash.com/200x200?engelskirchen",
    "openingHours": {
      "sunday": {
        "from": "closed"
      },
      "Monday": {
        "from": "10 AM",
        "to": "17 PM"
      },
      "Tuesday": {
        "from": "10 AM",
        "to": "17 PM"
      },
      "Wednesday": {
        "from": "10 AM",
        "to": "17 PM"
      },
      "Thrusday": {
        "from": "10 AM",
        "to": "17 PM"
      },
      "Friday": {
        "from": "10 AM",
        "to": "17 PM"
      },
      "Saturday": {
        "from": "10 AM",
        "to": "13 PM"
      }
    },
    "address": {
      "streetAddress": "Albertsthal 13",
      "addressLocality": "Engelskirchen",
      "postalCode": "51766",
      "addressCountry": "DE"
    },
    "geo": { "lat": 50.98683, "lng": 7.38963 }
  },
  {
    "id": 6,
    "dealerId": 6,
    "name": "Autohaus am Goetheplatz",
    "logo": "https://source.unsplash.com/200x200?munich",
    "openingHours": {
      "sunday": {
        "from": "closed"
      },
      "Monday": {
        "from": "10 AM",
        "to": "17 PM"
      },
      "Tuesday": {
        "from": "10 AM",
        "to": "17 PM"
      },
      "Wednesday": {
        "from": "10 AM",
        "to": "17 PM"
      },
      "Thrusday": {
        "from": "10 AM",
        "to": "17 PM"
      },
      "Friday": {
        "from": "10 AM",
        "to": "17 PM"
      },
      "Saturday": {
        "from": "10 AM",
        "to": "13 PM"
      }
    },
    "address": {
      "streetAddress": "Lindwurmstraße 20-24",
      "addressLocality": "München",
      "postalCode": "80337",
      "addressCountry": "DE"
    },
    "geo": { "lat": 50.98683, "lng": 7.38963 }
  }
]
